setup.py
todot/__init__.py
todot/__main__.py
todot.egg-info/PKG-INFO
todot.egg-info/SOURCES.txt
todot.egg-info/dependency_links.txt
todot.egg-info/entry_points.txt
todot.egg-info/top_level.txt
todot.egg-info/zip-safe