Metadata-Version: 1.0
Name: todot
Version: 0.1
Summary: Simple todo list task dependency dotfile generator.
Home-page: https://github.com/calder/todot
Author: Calder Coalson
Author-email: caldercoalson@gmail.com
License: LICENSE.txt
Platform: UNKNOWN
